Metadata-Version: 1.0
Name: anndataview
Version: 0.0.1b1
Summary: Extension of the AnnData object for annotated views.
Home-page: UNKNOWN
Author: UNKNOWN
Author-email: UNKNOWN
License: UNKNOWN
Platform: UNKNOWN
